tests/run_zexus_tests.py
tests/test_all_phases.zx
tests/test_blockchain_features.zx
tests/test_complexity_features.zx
tests/test_core_integration.py
tests/test_phase10_ecosystem.zx
tests/test_phase1_modifiers.zx
tests/test_phase2_plugins.zx
tests/test_phase3_security.zx
tests/test_phase4_vfs.zx
tests/test_phase5_types.zx
tests/test_phase6_metaprogramming.zx
tests/test_phase7_optimization.zx
tests/test_phase9_advanced_types.zx
tests/test_security_features.py
tests/test_security_features.zx
tests/test_simple_zx.zx
tests/test_verification_simple.zx
zexus/__init__.py
zexus/__main__.py
zexus/advanced_types.py
zexus/builtin_modules.py
zexus/builtin_plugins.py
zexus/capability_system.py
zexus/compare_interpreter_compiler.py
zexus/complexity_system.py
zexus/concurrency_system.py
zexus/config.py
zexus/crypto_bridge.py
zexus/debug_sanitizer.py
zexus/dependency_injection.py
zexus/ecosystem.py
zexus/environment.py
zexus/environment_manager.py
zexus/error_reporter.py
zexus/evaluator_original.py
zexus/external_bridge.py
zexus/find_affected_imports.sh
zexus/hybrid_orchestrator.py
zexus/input_validation.py
zexus/lexer.py
zexus/logging.py
zexus/metaprogramming.py
zexus/module_cache.py
zexus/module_manager.py
zexus/object.py
zexus/optimization.py
zexus/persistence.py
zexus/plugin_system.py
zexus/policy_engine.py
zexus/purity_system.py
zexus/search_old_imports.sh
zexus/security.py
zexus/security_enforcement.py
zexus/stack_trace.py
zexus/stdlib_integration.py
zexus/strategy_recovery.py
zexus/syntax_validator.py
zexus/type_system.py
zexus/validation_system.py
zexus/virtual_filesystem.py
zexus/zexus_ast.py
zexus/zexus_token.py
zexus/access_control_system/__init__.py
zexus/access_control_system/access_control.py
zexus/blockchain/__init__.py
zexus/blockchain/crypto.py
zexus/blockchain/ledger.py
zexus/blockchain/transaction.py
zexus/cli/__init__.py
zexus/cli/main.py
zexus/cli/zpm.py
zexus/compiler/__init__.py
zexus/compiler/bytecode.py
zexus/compiler/compat_runtime.py
zexus-1.6.5.dist-info/licenses/LICENSE
zexus-1.6.5.dist-info/METADATA
zexus-1.6.5.dist-info/WHEEL
zexus-1.6.5.dist-info/entry_points.txt
zexus-1.6.5.dist-info/top_level.txt
zexus-1.6.5.dist-info/RECORD
